ratisbona_project_starter/__init__.py
ratisbona_project_starter/__main__.py
ratisbona_project_starter/packager.py
ratisbona_project_starter/licenses/_gplv2.py
ratisbona_project_starter/templates/_gitignore.py
ratisbona_project_starter-0.0.1.dist-info/METADATA
ratisbona_project_starter-0.0.1.dist-info/WHEEL
ratisbona_project_starter-0.0.1.dist-info/entry_points.txt
ratisbona_project_starter-0.0.1.dist-info/licenses/LICENSE
ratisbona_project_starter-0.0.1.dist-info/RECORD
