Metadata-Version: 2.1
Name: ratisbona_project_starter
Version: 0.0.1
Summary: An application sthat is able to start a python project in a manner that can be published
Project-URL: Homepage, https://sourceforge.net/projects/ratisbona-project-starter/
Author-email: Ulrich Schwenk <ulrich-schwenk@gmx.de>
License-File: LICENSE
Classifier: License :: OSI Approved :: GNU General Public License v2 (GPLv2)
Classifier: Operating System :: OS Independent
Classifier: Programming Language :: Python :: 3
Requires-Python: >=3.10
Requires-Dist: typer==0.9.0
Provides-Extra: dev
Requires-Dist: black[d]; extra == 'dev'
Requires-Dist: coverage; extra == 'dev'
Requires-Dist: mypy; extra == 'dev'
Requires-Dist: pylint; extra == 'dev'
